purequransearch/__init__.py
purequransearch/cli.py
purequransearch/concordance.py
purequransearch/corpora/__init__.py
purequransearch/corpora/en.ahmedali.xml
purequransearch/corpora/en.ahmedraza.xml
purequransearch/corpora/en.arberry.xml
purequransearch/corpora/en.daryabadi.xml
purequransearch/corpora/en.hilali.xml
purequransearch/corpora/en.itani.xml
purequransearch/corpora/en.maududi.xml
purequransearch/corpora/en.mubarakpuri.xml
purequransearch/corpora/en.pickthall.xml
purequransearch/corpora/en.qarai.xml
purequransearch/corpora/en.qaribullah.xml
purequransearch/corpora/en.sahih.xml
purequransearch/corpora/en.sarwar.xml
purequransearch/corpora/en.shakir.xml
purequransearch/corpora/en.transliteration.xml
purequransearch/corpora/en.wahiduddin.xml
purequransearch/corpora/en.yusufali.xml
purequransearch-0.0.4.dist-info/METADATA
purequransearch-0.0.4.dist-info/WHEEL
purequransearch-0.0.4.dist-info/entry_points.txt
purequransearch-0.0.4.dist-info/top_level.txt
purequransearch-0.0.4.dist-info/RECORD
