Metadata-Version: 2.1
Name: purequransearch
Version: 0.0.4
Summary: Search the Quran (in English) for words and phrases.
Author-email: Josiah Winslow <winslowjosiah@gmail.com>
Project-URL: Homepage, https://github.com/winslowjosiah/pure-quran-search
Project-URL: Issues, https://github.com/winslowjosiah/pure-quran-search/issues
Classifier: Programming Language :: Python :: 3
Classifier: License :: OSI Approved :: GNU General Public License v3 (GPLv3)
Classifier: Operating System :: OS Independent
Requires-Python: >=3.9
Requires-Dist: lxml >=5.0.0
